Workbook

Sheet Incial
A1: Variable | B1: Valor
A2: Eventos por semana | B2: 1 – 2
A3: Eventos por mes | B3: 5
A4: Eventos por año | B4: 60

Sheet Eventos
A1: Año | B1: Eventos anuales | C1: Eventos mensuales | D1: Crecimiento
A2: 2026 | B2: 60 | C2: 5 | D2: Año base
A3: 2027 | B3: 72 | C3: 6 | D3: =+((B3*100%)/B2)-100% -> 0.2
A4: 2028 | B4: 84 | C4: 7 | D4: =+((B4*100%)/B3)-100% -> 0.16666667
A5: 2029 | B5: 100 | C5: 8 | D5: =+((B5*100%)/B4)-100% -> 0.19047619
A6: 2030 | B6: 115 | C6: 9 – 10 | D6: =+((B6*100%)/B5)-100% -> 0.15
A7: 2031 | B7: 130 | C7: 11 | D7: =+((B7*100%)/B6)-100% -> 0.13043478
A8: 2032 | B8: 150 | C8: 12 – 13 | D8: =+((B8*100%)/B7)-100% -> 0.15384615
A9: 2033 | B9: 170 | C9: 14 | D9: =+((B9*100%)/B8)-100% -> 0.13333333
A10: 2034 | B10: 190 | C10: 16 | D10: =+((B10*100%)/B9)-100% -> 0.11764706
A11: 2035 | B11: 210 | C11: 17 – 18 | D11: =+((B11*100%)/B10)-100% -> 0.10526316
A12: 2036 | B12: 230 | C12: 19 | D12: =+((B12*100%)/B11)-100% -> 0.095238095
A13: 2037 | B13: 250 | C13: 21 | D13: =+((B13*100%)/B12)-100% -> 0.086956522

Sheet Por evento
A1: Fuente de ingreso | B1: Valor promedio | D1: Concepto | E1: Valor estimado | G1: Variable | H1: Valor | J1: Equipo | K1: Rango de precios en el mercado | M1: Equipo | N1: Precio unitario | O1: Cantidad | P1: Ingreso
A2: Publicidad | B2: =+E5 -> 3000000 | D2: Proyección de video institucional | E2: 1500000 | G2: Asistentes promedio | H2: 300 | J2: Pantalla inflable para cine | K2: $150.000 – $350.000 | M2: Pantalla inflable | N2: 315000 | O2: 1 | P2: =+O2*N2 -> 315000
A3: Venta de alimentos | B3: =+H6 -> 1350000 | D3: Activaciones de marca | E3: 1000000 | G3: Porcentaje de consumo | H3: 0.3 | J3: Proyector audiovisual | K3: $70.000 – $150.000 | M3: Proyector | N3: 135000 | O3: 1 | P3: =+O3*N3 -> 135000
A4: Alquiler de equipos | B4: =+P6 -> 870000 | D4: Menciones y presencia de marca | E4: 500000 | G4: Consumidores estimados | H4: =+H2*H3 -> 90 | J4: Sistema de sonido | K4: $60.000 – $120.000 | M4: Cabinas de sonido | N4: 120000 | O4: 1 | P4: =+O4*N4 -> 120000
A5: Total Ingreso Por evento | B5: =SUM(B2:B4) -> 5220000 | D5: Total Ingreso Por Publicidad | E5: =SUM(E2:E4) -> 3000000 | G5: Gasto promedio | H5: 15000 | J5: Sillas para eventos | K5: $800 – $2.000 por unidad | M5: Sillas | N5: 1000 | O5: 300 | P5: =+O5*N5 -> 300000
G6: Ingreso estimado | H6: =+H5*H4 -> 1350000 | M6: Total Ingresos Por Equipos | P6: =SUM(P2:P5) -> 870000

Sheet Ingresos Proyectados
A1: =+Eventos!A1 -> Año | B1: =+Eventos!B1 -> Eventos anuales | C1: Valor Promedio por evento | D1: Ingresos Anuales | E1: Ingresos Mensuales
A2: =+Eventos!A2 -> 2026 | B2: =+Eventos!B2 -> 60 | C2: =+'Por evento'!$B$5 -> 5220000 | D2: =+C2*B2 -> 313200000 | E2: =+D2/12 -> 26100000
A3: =+Eventos!A3 -> 2027 | B3: =+Eventos!B3 -> 72 | C3: =+'Por evento'!$B$5 -> 5220000 | D3: =+C3*B3 -> 375840000 | E3: =+D3/12 -> 31320000
A4: =+Eventos!A4 -> 2028 | B4: =+Eventos!B4 -> 84 | C4: =+'Por evento'!$B$5 -> 5220000 | D4: =+C4*B4 -> 438480000 | E4: =+D4/12 -> 36540000
A5: =+Eventos!A5 -> 2029 | B5: =+Eventos!B5 -> 100 | C5: =+'Por evento'!$B$5 -> 5220000 | D5: =+C5*B5 -> 522000000 | E5: =+D5/12 -> 43500000
A6: =+Eventos!A6 -> 2030 | B6: =+Eventos!B6 -> 115 | C6: =+'Por evento'!$B$5 -> 5220000 | D6: =+C6*B6 -> 600300000 | E6: =+D6/12 -> 50025000
A7: =+Eventos!A7 -> 2031 | B7: =+Eventos!B7 -> 130 | C7: =+'Por evento'!$B$5 -> 5220000 | D7: =+C7*B7 -> 678600000 | E7: =+D7/12 -> 56550000
A8: =+Eventos!A8 -> 2032 | B8: =+Eventos!B8 -> 150 | C8: =+'Por evento'!$B$5 -> 5220000 | D8: =+C8*B8 -> 783000000 | E8: =+D8/12 -> 65250000
A9: =+Eventos!A9 -> 2033 | B9: =+Eventos!B9 -> 170 | C9: =+'Por evento'!$B$5 -> 5220000 | D9: =+C9*B9 -> 887400000 | E9: =+D9/12 -> 73950000
A10: =+Eventos!A10 -> 2034 | B10: =+Eventos!B10 -> 190 | C10: =+'Por evento'!$B$5 -> 5220000 | D10: =+C10*B10 -> 991800000 | E10: =+D10/12 -> 82650000
A11: =+Eventos!A11 -> 2035 | B11: =+Eventos!B11 -> 210 | C11: =+'Por evento'!$B$5 -> 5220000 | D11: =+C11*B11 -> 1096200000 | E11: =+D11/12 -> 91350000
A12: =+Eventos!A12 -> 2036 | B12: =+Eventos!B12 -> 230 | C12: =+'Por evento'!$B$5 -> 5220000 | D12: =+C12*B12 -> 1200600000 | E12: =+D12/12 -> 100050000
A13: =+Eventos!A13 -> 2037 | B13: =+Eventos!B13 -> 250 | C13: =+'Por evento'!$B$5 -> 5220000 | D13: =+C13*B13 -> 1305000000 | E13: =+D13/12 -> 108750000

Sheet IPC
A1: =+Eventos!A1 -> Año | B1: =+Eventos!B1 -> Eventos anuales | C1: Valor Promedio por evento | D1: IPC | E1: Ingresos Anuales | F1: Ingresos Mensuales
A2: =+Eventos!A2 -> 2026 | B2: =+Eventos!B2 -> 60 | C2: =+'Por evento'!$B$5 -> 5220000 | D2: 0.05 | E2: =+C2*B2 -> 313200000 | F2: =+E2/12 -> 26100000
A3: =+Eventos!A3 -> 2027 | B3: =+Eventos!B3 -> 72 | C3: =+C2+(C2*D3) -> 5481000 | D3: 0.05 | E3: =+C3*B3 -> 394632000 | F3: =+E3/12 -> 32886000
A4: =+Eventos!A4 -> 2028 | B4: =+Eventos!B4 -> 84 | C4: =+C3+(C3*D4) -> 5755050 | D4: 0.05 | E4: =+C4*B4 -> 483424200 | F4: =+E4/12 -> 40285350
A5: =+Eventos!A5 -> 2029 | B5: =+Eventos!B5 -> 100 | C5: =+C4+(C4*D5) -> 6042802.5 | D5: 0.05 | E5: =+C5*B5 -> 604280250 | F5: =+E5/12 -> 50356688
A6: =+Eventos!A6 -> 2030 | B6: =+Eventos!B6 -> 115 | C6: =+C5+(C5*D6) -> 6344942.6 | D6: 0.05 | E6: =+C6*B6 -> 7.296684e+08 | F6: =+E6/12 -> 60805700
A7: =+Eventos!A7 -> 2031 | B7: =+Eventos!B7 -> 130 | C7: =+C6+(C6*D7) -> 6662189.8 | D7: 0.05 | E7: =+C7*B7 -> 8.6608467e+08 | F7: =+E7/12 -> 72173722
A8: =+Eventos!A8 -> 2032 | B8: =+Eventos!B8 -> 150 | C8: =+C7+(C7*D8) -> 6995299.2 | D8: 0.05 | E8: =+C8*B8 -> 1.0492949e+09 | F8: =+E8/12 -> 87441241
A9: =+Eventos!A9 -> 2033 | B9: =+Eventos!B9 -> 170 | C9: =+C8+(C8*D9) -> 7345064.2 | D9: 0.05 | E9: =+C9*B9 -> 1.2486609e+09 | F9: =+E9/12 -> 1.0405508e+08
A10: =+Eventos!A10 -> 2034 | B10: =+Eventos!B10 -> 190 | C10: =+C9+(C9*D10) -> 7712317.4 | D10: 0.05 | E10: =+C10*B10 -> 1.4653403e+09 | F10: =+E10/12 -> 1.2211169e+08
A11: =+Eventos!A11 -> 2035 | B11: =+Eventos!B11 -> 210 | C11: =+C10+(C10*D11) -> 8097933.3 | D11: 0.05 | E11: =+C11*B11 -> 1.700566e+09 | F11: =+E11/12 -> 1.4171383e+08
A12: =+Eventos!A12 -> 2036 | B12: =+Eventos!B12 -> 230 | C12: =+C11+(C11*D12) -> 8502830 | D12: 0.05 | E12: =+C12*B12 -> 1.9556509e+09 | F12: =+E12/12 -> 1.6297091e+08
A13: =+Eventos!A13 -> 2037 | B13: =+Eventos!B13 -> 250 | C13: =+C12+(C12*D13) -> 8927971.4 | D13: 0.05 | E13: =+C13*B13 -> 2.2319929e+09 | F13: =+E13/12 -> 1.8599941e+08
